fmt/__init__.py
fmt/fmt.py
fmt-0.3.1.dist-info/DESCRIPTION.rst
fmt-0.3.1.dist-info/METADATA
fmt-0.3.1.dist-info/RECORD
fmt-0.3.1.dist-info/WHEEL
fmt-0.3.1.dist-info/metadata.json
fmt-0.3.1.dist-info/top_level.txt
