Metadata-Version: 1.1
Name: fmt
Version: 0.3.1
Summary: f-strings(Python 3.6) style literal string interpolation.
Home-page: https://github.com/damnever/fmt
Author: damnever
Author-email: dxc.wolf@gmail.com
License: The BSD 3-Clause License
Keywords: f-strings,format,literal string interpolation
Platform: UNKNOWN
Classifier: Development Status :: 4 - Beta
Classifier: Intended Audience :: Developers
Classifier: Topic :: Utilities
Classifier: License :: OSI Approved :: BSD License
Classifier: Programming Language :: Python :: 2.7
Classifier: Programming Language :: Python :: 3.2
Classifier: Programming Language :: Python :: 3.3
Classifier: Programming Language :: Python :: 3.4
Classifier: Programming Language :: Python :: 3.5
